{"id": "vEa0Bt_9TAI", "uploader": "1TV Kabul \u062a\u0644\u0648\u06cc\u0632\u06cc\u0648\u0646 \u06cc\u06a9", "uploader_id": "1TVKabul", "uploader_url": "http://www.youtube.com/user/1TVKabul", "upload_date": "20140221", "license": "Standard YouTube License", "creator": null, "title": "1TV Pashot Short News12:00 PM 21.2.2014 \u062e\u0628\u0631\u0647\u0627\u06cc \u067e\u0634\u062a\u0648", "alt_title": null, "thumbnail": "https://i.ytimg.com/vi/vEa0Bt_9TAI/hqdefault.jpg", "description": "", "categories": ["News & Politics"], "tags": ["Kabul", "1tv", "1 tv", "1tv media", "channel 1", "entertainment", "afghan music", "afghan show", "afghani show", "Dari"], "subtitles": {}, "automatic_captions": {}, "duration": 238, "age_limit": 0, "annotations": null, "chapters": null, "webpage_url": "https://www.youtube.com/watch?v=vEa0Bt_9TAI", "view_count": 1615, "like_count": 5, "dislike_count": 2, "average_rating": 3.85714292526, "formats": [{"ext": "m4a", "format_note": "DASH audio", "acodec": "mp4a.40.5", "abr": 48, "container": "m4a_dash", "format_id": "139", "url": "https://r6---sn-4g5edne6.googlevideo.com/videoplayback?id=bc46b406dffd4c02&itag=139&source=youtube&requiressl=yes&mn=sn-4g5edne6&mm=31&initcwndbps=4172500&ei=q5uJWYm3N4W2VJKYhGA&pl=16&mv=m&ms=au&ratebypass=yes&mime=audio/mp4&gir=yes&clen=1418170&lmt=1393344714924557&dur=238.376&key=dg_yt0&mt=1502190367&signature=41BD2DFE2FA1D565A7928CC62357E880EE217DE0.84385D37475D26AF77AD5F0850D1E4B7C17AF649&ip=131.159.40.117&ipbits=0&expire=1502212107&sparams=ip,ipbits,expire,id,itag,source,requiressl,mn,mm,initcwndbps,ei,pl,mv,ms,ratebypass,mime,gir,clen,lmt,dur", "manifest_url": "https://manifest.googlevideo.com/api/manifest/dash/mn/sn-4g5edne6/expire/1502212107/mm/31/sparams/as%2Cei%2Chfr%2Cid%2Cinitcwndbps%2Cip%2Cipbits%2Citag%2Cmm%2Cmn%2Cms%2Cmv%2Cpl%2Cplayback_host%2Crequiressl%2Csource%2Cexpire/id/bc46b406dffd4c02/key/yt6/source/youtube/mt/1502190367/hfr/1/playback_host/r6---sn-4g5edne6.googlevideo.com/signature/76344A487A5E5F675A3B52E1410CFF6E69770190.83F670ABDAA507A711740AE87AD1471FF9E69D1E/initcwndbps/4172500/ei/q5uJWYm3N4W2VJKYhGA/as/fmp4_audio_clear%2Cfmp4_sd_hd_clear/itag/0/pl/16/ipbits/0/mv/m/requiressl/yes/ms/au/ip/131.159.40.117", "width": null, "height": null, "tbr": 48.644, "asr": 22050, "fps": null, "language": null, "filesize": 1418170, "vcodec": "none", "format": "139 - audio only (DASH audio)", "protocol": "https", "http_headers": {"User-Agent": "Mozilla/5.0 (X11; Linux x86_64; rv:10.0) Gecko/20150101 Firefox/47.0 (Chrome)", "Accept-Charset": "ISO-8859-1,utf-8;q=0.7,*;q=0.7", "Accept": "text/html,application/xhtml+xml,application/xml;q=0.9,*/*;q=0.8", "Accept-Encoding": "gzip, deflate", "Accept-Language": "en-us,en;q=0.5"}}, {"format_id": "171", "url": "https://r2---sn-4g5e6ns7.googlevideo.com/videoplayback?key=yt6&mm=31&mn=sn-4g5e6ns7&ei=q5uJWcfkF9e9VuiwpuAB&ms=au&mt=1502190367&mv=m&pl=16&clen=2640655&signature=AE4EC01D33B379F97503EF63884AED852209BB01.C172930BB09DE0DDBD3070FD2CEB9E8D5A5EA36B&sparams=clen%2Cdur%2Cei%2Cgir%2Cid%2Cinitcwndbps%2Cip%2Cipbits%2Citag%2Ckeepalive%2Clmt%2Cmime%2Cmm%2Cmn%2Cms%2Cmv%2Cpl%2Crequiressl%2Csource%2Cexpire&keepalive=yes&ip=131.159.40.117&requiressl=yes&itag=171&lmt=1393148703957076&id=o-ABQIVxer8aGMD2Oag0Y8i90LmfyQ3by2qdgZHsp18TqE&dur=238.238&source=youtube&mime=audio%2Fwebm&ipbits=0&initcwndbps=4172500&expire=1502212107&gir=yes&ratebypass=yes", "player_url": null, "ext": "webm", "acodec": "vorbis", "format_note": "DASH audio", "abr": 128, "filesize": 2640655, "tbr": 93.417, "fps": 1, "vcodec": "none", "format": "171 - audio only (DASH audio)", "protocol": "https", "http_headers": {"User-Agent": "Mozilla/5.0 (X11; Linux x86_64; rv:10.0) Gecko/20150101 Firefox/47.0 (Chrome)", "Accept-Charset": "ISO-8859-1,utf-8;q=0.7,*;q=0.7", "Accept": "text/html,application/xhtml+xml,application/xml;q=0.9,*/*;q=0.8", "Accept-Encoding": "gzip, deflate", "Accept-Language": "en-us,en;q=0.5"}}, {"ext": "m4a", "format_note": "DASH audio", "acodec": "mp4a.40.2", "abr": 128, "container": "m4a_dash", "format_id": "140", "url": "https://r6---sn-4g5edne6.googlevideo.com/videoplayback?id=bc46b406dffd4c02&itag=140&source=youtube&requiressl=yes&mn=sn-4g5edne6&mm=31&initcwndbps=4172500&ei=q5uJWYm3N4W2VJKYhGA&pl=16&mv=m&ms=au&ratebypass=yes&mime=audio/mp4&gir=yes&clen=3785425&lmt=1393344710113567&dur=238.306&key=dg_yt0&mt=1502190367&signature=27B00C839FA7FD642117CF1797BEA6E6D30A764F.75FAF547D93604819E01D0F3C4F44A4B04BA155E&ip=131.159.40.117&ipbits=0&expire=1502212107&sparams=ip,ipbits,expire,id,itag,source,requiressl,mn,mm,initcwndbps,ei,pl,mv,ms,ratebypass,mime,gir,clen,lmt,dur", "manifest_url": "https://manifest.googlevideo.com/api/manifest/dash/mn/sn-4g5edne6/expire/1502212107/mm/31/sparams/as%2Cei%2Chfr%2Cid%2Cinitcwndbps%2Cip%2Cipbits%2Citag%2Cmm%2Cmn%2Cms%2Cmv%2Cpl%2Cplayback_host%2Crequiressl%2Csource%2Cexpire/id/bc46b406dffd4c02/key/yt6/source/youtube/mt/1502190367/hfr/1/playback_host/r6---sn-4g5edne6.googlevideo.com/signature/76344A487A5E5F675A3B52E1410CFF6E69770190.83F670ABDAA507A711740AE87AD1471FF9E69D1E/initcwndbps/4172500/ei/q5uJWYm3N4W2VJKYhGA/as/fmp4_audio_clear%2Cfmp4_sd_hd_clear/itag/0/pl/16/ipbits/0/mv/m/requiressl/yes/ms/au/ip/131.159.40.117", "width": null, "height": null, "tbr": 128.065, "asr": 44100, "fps": null, "language": null, "filesize": 3785425, "vcodec": "none", "format": "140 - audio only (DASH audio)", "protocol": "https", "http_headers": {"User-Agent": "Mozilla/5.0 (X11; Linux x86_64; rv:10.0) Gecko/20150101 Firefox/47.0 (Chrome)", "Accept-Charset": "ISO-8859-1,utf-8;q=0.7,*;q=0.7", "Accept": "text/html,application/xhtml+xml,application/xml;q=0.9,*/*;q=0.8", "Accept-Encoding": "gzip, deflate", "Accept-Language": "en-us,en;q=0.5"}}, {"ext": "mp4", "height": 144, "format_note": "DASH video", "vcodec": "avc1.4d400c", "format_id": "160", "url": "https://r6---sn-4g5edne6.googlevideo.com/videoplayback?id=bc46b406dffd4c02&itag=160&source=youtube&requiressl=yes&mn=sn-4g5edne6&mm=31&initcwndbps=4172500&ei=q5uJWYm3N4W2VJKYhGA&pl=16&mv=m&ms=au&ratebypass=yes&mime=video/mp4&gir=yes&clen=3338786&lmt=1393344766268314&dur=238.201&key=dg_yt0&mt=1502190367&signature=29BB3519194B39E8DF2F745F6F2436E77B9F31B5.1D9FB11C5A3489D6347195CD8FB0FABD5221123F&ip=131.159.40.117&ipbits=0&expire=1502212107&sparams=ip,ipbits,expire,id,itag,source,requiressl,mn,mm,initcwndbps,ei,pl,mv,ms,ratebypass,mime,gir,clen,lmt,dur", "manifest_url": "https://manifest.googlevideo.com/api/manifest/dash/mn/sn-4g5edne6/expire/1502212107/mm/31/sparams/as%2Cei%2Chfr%2Cid%2Cinitcwndbps%2Cip%2Cipbits%2Citag%2Cmm%2Cmn%2Cms%2Cmv%2Cpl%2Cplayback_host%2Crequiressl%2Csource%2Cexpire/id/bc46b406dffd4c02/key/yt6/source/youtube/mt/1502190367/hfr/1/playback_host/r6---sn-4g5edne6.googlevideo.com/signature/76344A487A5E5F675A3B52E1410CFF6E69770190.83F670ABDAA507A711740AE87AD1471FF9E69D1E/initcwndbps/4172500/ei/q5uJWYm3N4W2VJKYhGA/as/fmp4_audio_clear%2Cfmp4_sd_hd_clear/itag/0/pl/16/ipbits/0/mv/m/requiressl/yes/ms/au/ip/131.159.40.117", "width": 192, "tbr": 114.93, "asr": null, "fps": 15, "language": null, "filesize": 3338786, "acodec": "none", "format": "160 - 192x144 (DASH video)", "protocol": "https", "http_headers": {"User-Agent": "Mozilla/5.0 (X11; Linux x86_64; rv:10.0) Gecko/20150101 Firefox/47.0 (Chrome)", "Accept-Charset": "ISO-8859-1,utf-8;q=0.7,*;q=0.7", "Accept": "text/html,application/xhtml+xml,application/xml;q=0.9,*/*;q=0.8", "Accept-Encoding": "gzip, deflate", "Accept-Language": "en-us,en;q=0.5"}}, {"ext": "mp4", "height": 240, "format_note": "DASH video", "vcodec": "avc1.4d400d", "format_id": "133", "url": "https://r6---sn-4g5edne6.googlevideo.com/videoplayback?id=bc46b406dffd4c02&itag=133&source=youtube&requiressl=yes&mn=sn-4g5edne6&mm=31&initcwndbps=4172500&ei=q5uJWYm3N4W2VJKYhGA&pl=16&mv=m&ms=au&ratebypass=yes&mime=video/mp4&gir=yes&clen=7345415&lmt=1393344750023917&dur=238.201&key=dg_yt0&mt=1502190367&signature=6342BCB5DD95AC2B3EDA9F466A236E98A65A0792.06EACA12AECF7CAD95DD368B28A53D48638678A6&ip=131.159.40.117&ipbits=0&expire=1502212107&sparams=ip,ipbits,expire,id,itag,source,requiressl,mn,mm,initcwndbps,ei,pl,mv,ms,ratebypass,mime,gir,clen,lmt,dur", "manifest_url": "https://manifest.googlevideo.com/api/manifest/dash/mn/sn-4g5edne6/expire/1502212107/mm/31/sparams/as%2Cei%2Chfr%2Cid%2Cinitcwndbps%2Cip%2Cipbits%2Citag%2Cmm%2Cmn%2Cms%2Cmv%2Cpl%2Cplayback_host%2Crequiressl%2Csource%2Cexpire/id/bc46b406dffd4c02/key/yt6/source/youtube/mt/1502190367/hfr/1/playback_host/r6---sn-4g5edne6.googlevideo.com/signature/76344A487A5E5F675A3B52E1410CFF6E69770190.83F670ABDAA507A711740AE87AD1471FF9E69D1E/initcwndbps/4172500/ei/q5uJWYm3N4W2VJKYhGA/as/fmp4_audio_clear%2Cfmp4_sd_hd_clear/itag/0/pl/16/ipbits/0/mv/m/requiressl/yes/ms/au/ip/131.159.40.117", "width": 320, "tbr": 258.586, "asr": null, "fps": 25, "language": null, "filesize": 7345415, "acodec": "none", "format": "133 - 320x240 (DASH video)", "protocol": "https", "http_headers": {"User-Agent": "Mozilla/5.0 (X11; Linux x86_64; rv:10.0) Gecko/20150101 Firefox/47.0 (Chrome)", "Accept-Charset": "ISO-8859-1,utf-8;q=0.7,*;q=0.7", "Accept": "text/html,application/xhtml+xml,application/xml;q=0.9,*/*;q=0.8", "Accept-Encoding": "gzip, deflate", "Accept-Language": "en-us,en;q=0.5"}}, {"ext": "mp4", "height": 360, "format_note": "DASH video", "vcodec": "avc1.4d4015", "format_id": "134", "url": "https://r6---sn-4g5edne6.googlevideo.com/videoplayback?id=bc46b406dffd4c02&itag=134&source=youtube&requiressl=yes&mn=sn-4g5edne6&mm=31&initcwndbps=4172500&ei=q5uJWYm3N4W2VJKYhGA&pl=16&mv=m&ms=au&ratebypass=yes&mime=video/mp4&gir=yes&clen=8374783&lmt=1393344775157339&dur=238.201&key=dg_yt0&mt=1502190367&signature=16D08ABF850279884A289F307B79440807B935A6.23CA449B5B256153348ED91B98EB6CF1EE5EBA19&ip=131.159.40.117&ipbits=0&expire=1502212107&sparams=ip,ipbits,expire,id,itag,source,requiressl,mn,mm,initcwndbps,ei,pl,mv,ms,ratebypass,mime,gir,clen,lmt,dur", "manifest_url": "https://manifest.googlevideo.com/api/manifest/dash/mn/sn-4g5edne6/expire/1502212107/mm/31/sparams/as%2Cei%2Chfr%2Cid%2Cinitcwndbps%2Cip%2Cipbits%2Citag%2Cmm%2Cmn%2Cms%2Cmv%2Cpl%2Cplayback_host%2Crequiressl%2Csource%2Cexpire/id/bc46b406dffd4c02/key/yt6/source/youtube/mt/1502190367/hfr/1/playback_host/r6---sn-4g5edne6.googlevideo.com/signature/76344A487A5E5F675A3B52E1410CFF6E69770190.83F670ABDAA507A711740AE87AD1471FF9E69D1E/initcwndbps/4172500/ei/q5uJWYm3N4W2VJKYhGA/as/fmp4_audio_clear%2Cfmp4_sd_hd_clear/itag/0/pl/16/ipbits/0/mv/m/requiressl/yes/ms/au/ip/131.159.40.117", "width": 480, "tbr": 594.97, "asr": null, "fps": 25, "language": null, "filesize": 8374783, "acodec": "none", "format": "134 - 480x360 (DASH video)", "protocol": "https", "http_headers": {"User-Agent": "Mozilla/5.0 (X11; Linux x86_64; rv:10.0) Gecko/20150101 Firefox/47.0 (Chrome)", "Accept-Charset": "ISO-8859-1,utf-8;q=0.7,*;q=0.7", "Accept": "text/html,application/xhtml+xml,application/xml;q=0.9,*/*;q=0.8", "Accept-Encoding": "gzip, deflate", "Accept-Language": "en-us,en;q=0.5"}}, {"ext": "mp4", "height": 480, "format_note": "DASH video", "vcodec": "avc1.4d401e", "format_id": "135", "url": "https://r6---sn-4g5edne6.googlevideo.com/videoplayback?id=bc46b406dffd4c02&itag=135&source=youtube&requiressl=yes&mn=sn-4g5edne6&mm=31&initcwndbps=4172500&ei=q5uJWYm3N4W2VJKYhGA&pl=16&mv=m&ms=au&ratebypass=yes&mime=video/mp4&gir=yes&clen=17196505&lmt=1393344748831846&dur=238.201&key=dg_yt0&mt=1502190367&signature=2A30EF1D07FFC6DE1FDEFED69EB1BB37207796BE.4B68F65AB4D0594CCB2719EF32B4D564F368AA46&ip=131.159.40.117&ipbits=0&expire=1502212107&sparams=ip,ipbits,expire,id,itag,source,requiressl,mn,mm,initcwndbps,ei,pl,mv,ms,ratebypass,mime,gir,clen,lmt,dur", "manifest_url": "https://manifest.googlevideo.com/api/manifest/dash/mn/sn-4g5edne6/expire/1502212107/mm/31/sparams/as%2Cei%2Chfr%2Cid%2Cinitcwndbps%2Cip%2Cipbits%2Citag%2Cmm%2Cmn%2Cms%2Cmv%2Cpl%2Cplayback_host%2Crequiressl%2Csource%2Cexpire/id/bc46b406dffd4c02/key/yt6/source/youtube/mt/1502190367/hfr/1/playback_host/r6---sn-4g5edne6.googlevideo.com/signature/76344A487A5E5F675A3B52E1410CFF6E69770190.83F670ABDAA507A711740AE87AD1471FF9E69D1E/initcwndbps/4172500/ei/q5uJWYm3N4W2VJKYhGA/as/fmp4_audio_clear%2Cfmp4_sd_hd_clear/itag/0/pl/16/ipbits/0/mv/m/requiressl/yes/ms/au/ip/131.159.40.117", "width": 640, "tbr": 1102.737, "asr": null, "fps": 25, "language": null, "filesize": 17196505, "acodec": "none", "format": "135 - 640x480 (DASH video)", "protocol": "https", "http_headers": {"User-Agent": "Mozilla/5.0 (X11; Linux x86_64; rv:10.0) Gecko/20150101 Firefox/47.0 (Chrome)", "Accept-Charset": "ISO-8859-1,utf-8;q=0.7,*;q=0.7", "Accept": "text/html,application/xhtml+xml,application/xml;q=0.9,*/*;q=0.8", "Accept-Encoding": "gzip, deflate", "Accept-Language": "en-us,en;q=0.5"}}, {"format_id": "17", "url": "https://r2---sn-4g5e6ns7.googlevideo.com/videoplayback?key=yt6&mm=31&mn=sn-4g5e6ns7&ei=q5uJWcfkF9e9VuiwpuAB&ms=au&mt=1502190367&mv=m&pl=16&clen=2437226&signature=A116142E9DB820756BAD88F3EE7E7C3DB89893D7.D63BE166895337019AE13B7957E8CA1159F21EF6&mime=video%2F3gpp&ip=131.159.40.117&requiressl=yes&itag=17&lmt=1393344789405094&id=o-ABQIVxer8aGMD2Oag0Y8i90LmfyQ3by2qdgZHsp18TqE&dur=238.561&source=youtube&sparams=clen%2Cdur%2Cei%2Cgir%2Cid%2Cinitcwndbps%2Cip%2Cipbits%2Citag%2Clmt%2Cmime%2Cmm%2Cmn%2Cms%2Cmv%2Cpl%2Crequiressl%2Csource%2Cexpire&ipbits=0&initcwndbps=4172500&expire=1502212107&gir=yes&ratebypass=yes", "player_url": null, "ext": "3gp", "width": 176, "height": 144, "acodec": "mp4a.40.2", "abr": 24, "vcodec": "mp4v.20.3", "resolution": "176x144", "format_note": "small", "format": "17 - 176x144 (small)", "protocol": "https", "http_headers": {"User-Agent": "Mozilla/5.0 (X11; Linux x86_64; rv:10.0) Gecko/20150101 Firefox/47.0 (Chrome)", "Accept-Charset": "ISO-8859-1,utf-8;q=0.7,*;q=0.7", "Accept": "text/html,application/xhtml+xml,application/xml;q=0.9,*/*;q=0.8", "Accept-Encoding": "gzip, deflate", "Accept-Language": "en-us,en;q=0.5"}}, {"format_id": "36", "url": "https://r2---sn-4g5e6ns7.googlevideo.com/videoplayback?key=yt6&mm=31&mn=sn-4g5e6ns7&ei=q5uJWcfkF9e9VuiwpuAB&ms=au&mt=1502190367&mv=m&pl=16&clen=6803880&signature=6C376D452FCA996A7425293153ACECBDD1B963FB.C2D2EB329FBE4BC90FFBE4332270E8595DB5C9F3&mime=video%2F3gpp&ip=131.159.40.117&requiressl=yes&itag=36&lmt=1393344814858598&id=o-ABQIVxer8aGMD2Oag0Y8i90LmfyQ3by2qdgZHsp18TqE&dur=238.422&source=youtube&sparams=clen%2Cdur%2Cei%2Cgir%2Cid%2Cinitcwndbps%2Cip%2Cipbits%2Citag%2Clmt%2Cmime%2Cmm%2Cmn%2Cms%2Cmv%2Cpl%2Crequiressl%2Csource%2Cexpire&ipbits=0&initcwndbps=4172500&expire=1502212107&gir=yes&ratebypass=yes", "player_url": null, "ext": "3gp", "width": 320, "acodec": "mp4a.40.2", "vcodec": "mp4v.20.3", "resolution": "320x240", "height": 240, "format_note": "small", "format": "36 - 320x240 (small)", "protocol": "https", "http_headers": {"User-Agent": "Mozilla/5.0 (X11; Linux x86_64; rv:10.0) Gecko/20150101 Firefox/47.0 (Chrome)", "Accept-Charset": "ISO-8859-1,utf-8;q=0.7,*;q=0.7", "Accept": "text/html,application/xhtml+xml,application/xml;q=0.9,*/*;q=0.8", "Accept-Encoding": "gzip, deflate", "Accept-Language": "en-us,en;q=0.5"}}, {"format_id": "18", "url": "https://r2---sn-4g5e6ns7.googlevideo.com/videoplayback?key=yt6&mm=31&mn=sn-4g5e6ns7&ei=q5uJWcfkF9e9VuiwpuAB&ms=au&mt=1502190367&mv=m&pl=16&clen=11398179&signature=4463A1DE6E0D456A79088A9CE306614C8B645F26.4CA44BE823BF0D384AA8623A9CB222FF55ABE4E4&sparams=clen%2Cdur%2Cei%2Cgir%2Cid%2Cinitcwndbps%2Cip%2Cipbits%2Citag%2Clmt%2Cmime%2Cmm%2Cmn%2Cms%2Cmv%2Cpl%2Cratebypass%2Crequiressl%2Csource%2Cexpire&ip=131.159.40.117&requiressl=yes&itag=18&lmt=1393344794814444&id=o-ABQIVxer8aGMD2Oag0Y8i90LmfyQ3by2qdgZHsp18TqE&dur=238.306&source=youtube&mime=video%2Fmp4&ipbits=0&ratebypass=yes&initcwndbps=4172500&expire=1502212107&gir=yes", "player_url": null, "ext": "mp4", "width": 480, "height": 360, "acodec": "mp4a.40.2", "abr": 96, "vcodec": "avc1.42001E", "resolution": "480x360", "format_note": "medium", "format": "18 - 480x360 (medium)", "protocol": "https", "http_headers": {"User-Agent": "Mozilla/5.0 (X11; Linux x86_64; rv:10.0) Gecko/20150101 Firefox/47.0 (Chrome)", "Accept-Charset": "ISO-8859-1,utf-8;q=0.7,*;q=0.7", "Accept": "text/html,application/xhtml+xml,application/xml;q=0.9,*/*;q=0.8", "Accept-Encoding": "gzip, deflate", "Accept-Language": "en-us,en;q=0.5"}}, {"format_id": "43", "url": "https://r2---sn-4g5e6ns7.googlevideo.com/videoplayback?key=yt6&mm=31&mn=sn-4g5e6ns7&ei=q5uJWcfkF9e9VuiwpuAB&ms=au&mt=1502190367&mv=m&pl=16&clen=13373428&signature=6418DC65467689EAEA34B8F1B1147292715DAA75.CD2E0F82E6CE965D57BB28689C241D53A828865E&sparams=clen%2Cdur%2Cei%2Cgir%2Cid%2Cinitcwndbps%2Cip%2Cipbits%2Citag%2Clmt%2Cmime%2Cmm%2Cmn%2Cms%2Cmv%2Cpl%2Cratebypass%2Crequiressl%2Csource%2Cexpire&ip=131.159.40.117&requiressl=yes&itag=43&lmt=1392973045261932&id=o-ABQIVxer8aGMD2Oag0Y8i90LmfyQ3by2qdgZHsp18TqE&dur=0.000&source=youtube&mime=video%2Fwebm&ipbits=0&ratebypass=yes&initcwndbps=4172500&expire=1502212107&gir=yes", "player_url": null, "ext": "webm", "width": 640, "height": 360, "acodec": "vorbis", "abr": 128, "vcodec": "vp8.0", "resolution": "640x360", "format_note": "medium", "format": "43 - 640x360 (medium)", "protocol": "https", "http_headers": {"User-Agent": "Mozilla/5.0 (X11; Linux x86_64; rv:10.0) Gecko/20150101 Firefox/47.0 (Chrome)", "Accept-Charset": "ISO-8859-1,utf-8;q=0.7,*;q=0.7", "Accept": "text/html,application/xhtml+xml,application/xml;q=0.9,*/*;q=0.8", "Accept-Encoding": "gzip, deflate", "Accept-Language": "en-us,en;q=0.5"}}], "is_live": null, "start_time": null, "end_time": null, "series": null, "season_number": null, "episode_number": null, "extractor": "youtube", "webpage_url_basename": "vEa0Bt_9TAI", "extractor_key": "Youtube", "playlist": null, "playlist_index": null, "thumbnails": [{"url": "https://i.ytimg.com/vi/vEa0Bt_9TAI/hqdefault.jpg", "id": "0"}], "display_id": "vEa0Bt_9TAI", "ext": "mp4", "height": 480, "format_note": "DASH video", "vcodec": "avc1.4d401e", "format_id": "135", "url": "https://r6---sn-4g5edne6.googlevideo.com/videoplayback?id=bc46b406dffd4c02&itag=135&source=youtube&requiressl=yes&mn=sn-4g5edne6&mm=31&initcwndbps=4172500&ei=q5uJWYm3N4W2VJKYhGA&pl=16&mv=m&ms=au&ratebypass=yes&mime=video/mp4&gir=yes&clen=17196505&lmt=1393344748831846&dur=238.201&key=dg_yt0&mt=1502190367&signature=2A30EF1D07FFC6DE1FDEFED69EB1BB37207796BE.4B68F65AB4D0594CCB2719EF32B4D564F368AA46&ip=131.159.40.117&ipbits=0&expire=1502212107&sparams=ip,ipbits,expire,id,itag,source,requiressl,mn,mm,initcwndbps,ei,pl,mv,ms,ratebypass,mime,gir,clen,lmt,dur", "manifest_url": "https://manifest.googlevideo.com/api/manifest/dash/mn/sn-4g5edne6/expire/1502212107/mm/31/sparams/as%2Cei%2Chfr%2Cid%2Cinitcwndbps%2Cip%2Cipbits%2Citag%2Cmm%2Cmn%2Cms%2Cmv%2Cpl%2Cplayback_host%2Crequiressl%2Csource%2Cexpire/id/bc46b406dffd4c02/key/yt6/source/youtube/mt/1502190367/hfr/1/playback_host/r6---sn-4g5edne6.googlevideo.com/signature/76344A487A5E5F675A3B52E1410CFF6E69770190.83F670ABDAA507A711740AE87AD1471FF9E69D1E/initcwndbps/4172500/ei/q5uJWYm3N4W2VJKYhGA/as/fmp4_audio_clear%2Cfmp4_sd_hd_clear/itag/0/pl/16/ipbits/0/mv/m/requiressl/yes/ms/au/ip/131.159.40.117", "width": 640, "tbr": 1102.737, "asr": null, "fps": 25, "language": null, "filesize": 17196505, "acodec": "none", "format": "135 - 640x480 (DASH video)", "protocol": "https", "http_headers": {"User-Agent": "Mozilla/5.0 (X11; Linux x86_64; rv:10.0) Gecko/20150101 Firefox/47.0 (Chrome)", "Accept-Charset": "ISO-8859-1,utf-8;q=0.7,*;q=0.7", "Accept": "text/html,application/xhtml+xml,application/xml;q=0.9,*/*;q=0.8", "Accept-Encoding": "gzip, deflate", "Accept-Language": "en-us,en;q=0.5"}, "fulltitle": "1TV Pashot Short News12:00 PM 21.2.2014 \u062e\u0628\u0631\u0647\u0627\u06cc \u067e\u0634\u062a\u0648", "_filename": "vEa0Bt_9TAI.mp4"}